glassfrog/__init__.py
glassfrog/client.py
glassfrog/exceptions.py
glassfrog/models.py
glassfrog-0.4.2.dist-info/WHEEL
glassfrog-0.4.2.dist-info/METADATA
glassfrog-0.4.2.dist-info/RECORD
