Metadata-Version: 2.1
Name: glassfrog
Version: 0.4.2
Summary: Python client for Glassfrog API
Author: Joao Daher
Author-email: joao@daher.dev
Requires-Python: >=3.7,<3.10
Classifier: Programming Language :: Python :: 3
Classifier: Programming Language :: Python :: 3.7
Classifier: Programming Language :: Python :: 3.8
Classifier: Programming Language :: Python :: 3.9
Requires-Dist: requests
Requires-Dist: retrying
